{   
    "name": "level-3",
    "description": "Đây là một màn chơi tìm điểm khác biệt",
    "points": [
        {
            "x": 0.6152230798887677,
            "y": 0.5072172503082951,
            "r": 0.08
        },
        {
            "x": 0.5933484814927226,
            "y": 0.7984228414556451,
            "r": 0.1
        },
        {
            "x": 0.3390562751386986,
            "y": 0.6083872678900035,
            "r": 0.08
        },
        {
            "x": 0.1749967871683606,
            "y": 0.43885913032065427,
            "r": 0.08
        },
        {
            "x": 0.9154920317677377,
            "y": 0.7051096618103402,
            "r": 0.08
        }
    ],
    "img_1": "3_1.jpg",
    "img_2": "3_2.jpg",
    "time": 90
}